LICENSE
MANIFEST.in
README.md
setup.cfg
setup.py
stdin_tagger.py
stdin_tagger.egg-info/PKG-INFO
stdin_tagger.egg-info/SOURCES.txt
stdin_tagger.egg-info/dependency_links.txt
stdin_tagger.egg-info/entry_points.txt
stdin_tagger.egg-info/requires.txt
stdin_tagger.egg-info/top_level.txt