Metadata-Version: 2.1
Name: stdin-tagger
Version: 1.1.0
Summary: decorate stdin with current timestamp and optional tag
Home-page: http://msztolcman.github.io/stdin-tagger/
Author: Marcin Sztolcman
Author-email: marcin@urzenia.net
License: MIT
Keywords: timestamp decorate tag stdin
Platform: UNKNOWN
Classifier: Development Status :: 4 - Beta
Classifier: Environment :: Console
Classifier: Intended Audience :: Developers
Classifier: License :: OSI Approved :: MIT License
Classifier: Topic :: Utilities
Classifier: Topic :: Software Development
Classifier: Programming Language :: Python :: 3.3
Classifier: Programming Language :: Python :: 3.4
Classifier: Programming Language :: Python :: 3.5
Classifier: Programming Language :: Python :: 3.6
Classifier: Programming Language :: Python :: 3.7
Classifier: Programming Language :: Python :: 3.8
